<?xml version="1.0" encoding="UTF-8"?>
<suite name="Test form">
	<test name="SysAid Testing">
		<classes>
			<class name ="com.totalamber.qa.SysAidLoginTest">
				<methods>
					<include name = "loginSysAid"/>
				</methods>
			</class>
			<class name ="com.totalamber.qa.SysAidHomeTest">
				<methods>
					<include name = "caseSearch"/>
				</methods>
			</class>
			<class name ="com.totalamber.qa.SysAidResolveTest">
				<methods>
					<include name = "verifySysAidUserAbleToResolveCase"/>
				</methods>
			</class>
		</classes>
	</test>
</suite>











<!--
<?xml version="1.0" encoding="UTF-8"?>
<suite name="Test form">
	<test name="Cases">
		<classes>
			<class name="com.totalamber.qa.SysAidLoginTest">
				<methods>
					<include name="AssignCase"/>
				</methods>
			</class>
		</classes>
	</test>
</suite>
-->






